{
"data":[
     {
        "title":"Action Comics #1","date":"06/01/1938","average":"4.18", "population":"44"
    },
    {
        "title":"Detective Comics #27","date":"05/01/1939","average":"4.59", "population":"38"
    },
    {
        "title":"Superman #1","date":"07/01/1939","average":"2.51", "population":"78"
    },
    {
        "title":"Marvel Comics #1","date":"11/01/39","average":"4.27", "population":"37"
    },
    {
        "title":"Batman #1","date":"03/01/1940","average":"3.20", "population":"153"
    },
    {
        "title":"All American Comics #16","date":"7/01/1940","average":"4.10", "population":"33"
    },
    {
        "title":"Captain America Comics #1","date":"03/01/1941","average":"5.10", "population":"97"
    },
    {
        "title":"Action Comics #1","date":"","average":"", "population":""
    },
    {
        "title":"Action Comics #1","date":"","average":"", "population":""
    },
    {
        "title":"Action Comics #1","date":"","average":"", "population":""
    }

    ]

}











Action Comics #7
D.C. Comics, 12/38	
Jerry Siegel and Fred Guardineer stories		2nd Superman cover.
Fred Guardineer and Bernard Baily art		
Joe Shuster cover and art		

 Books	CGC Label	CGC Total	Avg. Grade	10	9.9	9.8	9.6	9.4	9.2	9.0	8.5	8.0	7.5	7.0	6.5	6.0	5.5	5.0	4.5	4.0	3.5	3.0	2.5	2.0	1.8	1.5	1.0	0.5
1 BOOK	Universal	33	3.28



Pep Comics #22
MLJ Magazines, 12/41	
Vic Bloom, Harry Shorten & Joe Blair		1st appearance of Archie Andrews,
stories, Paul Reinman & Bob Montana art		Betty Cooper & Jughead
Irv Novick cover & art		(Forsythe P. Jones).

 Books	CGC Label	CGC Total	Avg. Grade	10	9.9	9.8	9.6	9.4	9.2	9.0	8.5	8.0	7.5	7.0	6.5	6.0	5.5	5.0	4.5	4.0	3.5	3.0	2.5	2.0	1.8	1.5	1.0	0.5
1 BOOK	Universal	21	3.24

Action Comics #10
D.C. Comics, 3/39	
Jerry Siegel story, Joe Shuster cover		3rd Superman cover.
Joe Shuster, Fred Guardineer,		
Sheldon Moldoff and Bernard Baily art		

 Books	CGC Label	CGC Total	Avg. Grade	10	9.9	9.8	9.6	9.4	9.2	9.0	8.5	8.0	7.5	7.0	6.5	6.0	5.5	5.0	4.5	4.0	3.5	3.0	2.5	2.0	1.8	1.5	1.0	0.5
1 BOOK	Universal	24	3.35

All Star Comics #8
D.C. Comics, 12/41-1/42	
Gardner Fox & William Marston stories		Origin & 1st appearance of Wonder Woman.
Burnley, Moldoff, Baily & Peter art		Starman & Doctor Mid-Nite join JSA.
Everett E. Hibbard cover & art		Green Lantern becomes Honorary Member.

 Books	CGC Label	CGC Total	Avg. Grade	10	9.9	9.8	9.6	9.4	9.2	9.0	8.5	8.0	7.5	7.0	6.5	6.0	5.5	5.0	4.5	4.0	3.5	3.0	2.5	2.0	1.8	1.5	1.0	0.5
1 BOOK	Universal	153	3.79

Detective Comics #31
D.C. Comics, 9/39	
Gardner Fox and Jerry Siegel stories		Classic cover. 1st Batplane.
Fred Guardineer and Joe Shuster art		1st appearance of the Monk
Bob Kane cover and art		and Julie Madison.

 Books	CGC Label	CGC Total	Avg. Grade	10	9.9	9.8	9.6	9.4	9.2	9.0	8.5	8.0	7.5	7.0	6.5	6.0	5.5	5.0	4.5	4.0	3.5	3.0	2.5	2.0	1.8	1.5	1.0	0.5
1 BOOK	Universal	66	2.97"
}
